{"version":"0.4","title":"various-features-blocks-5","type":"section","content":[{"id":"339473e6","settings":{"background_background":"classic","background_position":"center center","background_attachment":"fixed","background_size":"cover","padding":{"unit":"px","top":"150","right":"0","bottom":"150","left":"0","isLinked":false},"padding_tablet":{"unit":"px","top":"80","right":"30","bottom":"80","left":"30","isLinked":false},"padding_mobile":{"unit":"px","top":"50","right":"15","bottom":"50","left":"15","isLinked":false}},"elements":[{"id":"31eea514","settings":{"_column_size":100,"_inline_size":null,"_inline_size_tablet":100,"_inline_size_mobile":100,"padding":{"unit":"px","top":"0","right":"0","bottom":"0","left":"0","isLinked":true},"padding_mobile":{"unit":"px","top":"0","right":"0","bottom":"0","left":"0","isLinked":true},"content_position":"center"},"elements":[{"id":"304385dd","settings":{"content_width":{"unit":"px","size":600}},"elements":[{"id":"5288b4d5","settings":{"_column_size":100,"_inline_size":null,"_inline_size_mobile":100},"elements":[{"id":"206b341c","settings":{"title":"Listen to Me","align":"center","header_size":"h5","title_color":"#a2a2a2","typography_typography":"custom","typography_font_family":"Pacifico","_margin":{"unit":"px","top":"0","right":"0","bottom":"-10","left":"0","isLinked":false},"typography_font_size":{"unit":"px","size":25,"sizes":[]}},"elements":[],"isInner":false,"widgetType":"heading","elType":"widget"},{"id":"2b8d3856","settings":{"title":"Event Speakers","align":"center","typography_typography":"custom","typography_font_family":"Pacifico","_margin":{"unit":"px","top":"0","right":"0","bottom":"0","left":"0","isLinked":false},"title_color":"#444444","typography_font_size":{"unit":"px","size":62,"sizes":[]},"typography_font_size_mobile":{"unit":"px","size":36,"sizes":[]}},"elements":[],"isInner":false,"widgetType":"heading","elType":"widget"},{"id":"4f3bb49e","settings":{"editor":"<p>Lorem ipsum dolor sit amet, consectetur adipiscing elit. Ut elit tellus, luctus nec ullamcorper mattis, pulvinar dapibus leo.<\/p>","align":"center","typography_typography":"custom"},"elements":[],"isInner":false,"widgetType":"text-editor","elType":"widget"},{"id":"1a57eb9d","settings":{"style":"dashed","weight":{"unit":"px","size":3,"sizes":[]},"color":"#f84e7c","width":{"unit":"%","size":21,"sizes":[]},"align":"center","gap":{"unit":"px","size":0,"sizes":[]}},"elements":[],"isInner":false,"widgetType":"divider","elType":"widget"}],"isInner":true,"elType":"column"}],"isInner":true,"elType":"section"},{"id":"449d29fb","settings":{"gap":"wide","padding":{"unit":"px","top":"50","right":"0","bottom":"0","left":"0","isLinked":false}},"elements":[{"id":"2d28d306","settings":{"_column_size":100,"_inline_size":null,"_inline_size_tablet":100,"_inline_size_mobile":100},"elements":[{"id":"faa2da0","settings":{"avd_gallery_images":[{"id":51575,"url":"https:\/\/bdthemes.net\/demo\/ready-pages\/ready-blocks\/wp-content\/uploads\/2019\/06\/musician-1.jpg"},{"id":51576,"url":"https:\/\/bdthemes.net\/demo\/ready-pages\/ready-blocks\/wp-content\/uploads\/2019\/06\/musician-2.jpg"},{"id":51577,"url":"https:\/\/bdthemes.net\/demo\/ready-pages\/ready-blocks\/wp-content\/uploads\/2019\/06\/musician-3.jpg"},{"id":51578,"url":"https:\/\/bdthemes.net\/demo\/ready-pages\/ready-blocks\/wp-content\/uploads\/2019\/06\/musician-4.jpg"},{"id":51579,"url":"https:\/\/bdthemes.net\/demo\/ready-pages\/ready-blocks\/wp-content\/uploads\/2019\/06\/musician-5.jpg"},{"id":51580,"url":"https:\/\/bdthemes.net\/demo\/ready-pages\/ready-blocks\/wp-content\/uploads\/2019\/06\/musician-6.jpg"},{"id":51581,"url":"https:\/\/bdthemes.net\/demo\/ready-pages\/ready-blocks\/wp-content\/uploads\/2019\/06\/musician-7.jpg"},{"id":51582,"url":"https:\/\/bdthemes.net\/demo\/ready-pages\/ready-blocks\/wp-content\/uploads\/2019\/06\/musician-8.jpg"}],"thumbnail_size":"full","show_caption":"yes","overlay_animation":"slide-left-medium","gallery_link_text":"Open Gallery","item_gap":{"unit":"px","size":30},"row_gap":{"unit":"px","size":30},"element_pack_widget_tooltip_text":"This is Tooltip","caption_color":"#000000","caption_typography_typography":"custom","caption_typography_font_size":{"unit":"px","size":15},"button_text_color":"#ffffff","link_image":{"url":"http:\/\/192.168.1.100\/element-pack\/wp-content\/plugins\/elementor\/assets\/images\/placeholder.png","id":""},"caption_typography_line_height_tablet":{"unit":"em","size":""},"caption_typography_line_height_mobile":{"unit":"em","size":""},"typography_line_height_tablet":{"unit":"em","size":""},"typography_line_height_mobile":{"unit":"em","size":""},"element_pack_widget_tooltip":"","element_pack_widget_tooltip_placement":"top","element_pack_widget_tooltip_animation":"shift-toward","element_pack_widget_tooltip_x_offset":0,"element_pack_widget_tooltip_y_offset":0,"element_pack_widget_tooltip_arrow":"","element_pack_widget_tooltip_width":{"unit":"px","size":""},"element_pack_widget_tooltip_width_tablet":{"unit":"px","size":""},"element_pack_widget_tooltip_width_mobile":{"unit":"px","size":""},"element_pack_widget_tooltip_color":"","element_pack_widget_tooltip_background_background":"","element_pack_widget_tooltip_background_color":"","element_pack_widget_tooltip_background_color_stop":{"unit":"%","size":0},"element_pack_widget_tooltip_background_color_b":"#f2295b","element_pack_widget_tooltip_background_color_b_stop":{"unit":"%","size":100},"element_pack_widget_tooltip_background_gradient_type":"linear","element_pack_widget_tooltip_background_gradient_angle":{"unit":"deg","size":180},"element_pack_widget_tooltip_background_gradient_position":"center center","element_pack_widget_tooltip_background_image":{"url":"","id":""},"element_pack_widget_tooltip_background_position":"","element_pack_widget_tooltip_background_attachment":"","element_pack_widget_tooltip_background_repeat":"","element_pack_widget_tooltip_background_size":"","element_pack_widget_tooltip_background_video_link":"","element_pack_widget_tooltip_background_video_start":"","element_pack_widget_tooltip_background_video_end":"","element_pack_widget_tooltip_background_video_fallback":{"url":"","id":""},"element_pack_widget_tooltip_arrow_color":"","element_pack_widget_tooltip_padding":{"unit":"px","top":"","right":"","bottom":"","left":"","isLinked":true},"element_pack_widget_tooltip_padding_tablet":{"unit":"px","top":"","right":"","bottom":"","left":"","isLinked":true},"element_pack_widget_tooltip_padding_mobile":{"unit":"px","top":"","right":"","bottom":"","left":"","isLinked":true},"element_pack_widget_tooltip_border_border":"","element_pack_widget_tooltip_border_width":{"unit":"px","top":"","right":"","bottom":"","left":"","isLinked":true},"element_pack_widget_tooltip_border_color":"","element_pack_widget_tooltip_border_radius":{"unit":"px","top":"","right":"","bottom":"","left":"","isLinked":true},"element_pack_widget_tooltip_border_radius_tablet":{"unit":"px","top":"","right":"","bottom":"","left":"","isLinked":true},"element_pack_widget_tooltip_border_radius_mobile":{"unit":"px","top":"","right":"","bottom":"","left":"","isLinked":true},"element_pack_widget_tooltip_text_align":"center","element_pack_widget_tooltip_box_shadow_box_shadow_type":"","element_pack_widget_tooltip_box_shadow_box_shadow":{"horizontal":0,"vertical":0,"blur":10,"spread":0,"color":"rgba(0,0,0,0.5)"},"element_pack_widget_tooltip_box_shadow_box_shadow_position":" ","element_pack_widget_tooltip_typography_typography":"","element_pack_widget_tooltip_typography_font_family":"","element_pack_widget_tooltip_typography_font_size":{"unit":"px","size":""},"element_pack_widget_tooltip_typography_font_size_tablet":{"unit":"px","size":""},"element_pack_widget_tooltip_typography_font_size_mobile":{"unit":"px","size":""},"element_pack_widget_tooltip_typography_font_weight":"","element_pack_widget_tooltip_typography_text_transform":"","element_pack_widget_tooltip_typography_font_style":"","element_pack_widget_tooltip_typography_text_decoration":"","element_pack_widget_tooltip_typography_line_height":{"unit":"em","size":""},"element_pack_widget_tooltip_typography_line_height_tablet":{"unit":"em","size":""},"element_pack_widget_tooltip_typography_line_height_mobile":{"unit":"em","size":""},"element_pack_widget_tooltip_typography_letter_spacing":{"unit":"px","size":""},"element_pack_widget_tooltip_typography_letter_spacing_tablet":{"unit":"px","size":""},"element_pack_widget_tooltip_typography_letter_spacing_mobile":{"unit":"px","size":""},"sticky":"","sticky_on":["desktop","tablet","mobile"],"sticky_offset":0,"sticky_effects_offset":0,"sticky_parent":"","custom_css":"","item_border_radius":{"unit":"px","top":"300","right":"300","bottom":"300","left":"300","isLinked":true},"background_color":"#000000","button_border_radius":{"unit":"px","top":"100","right":"100","bottom":"100","left":"100","isLinked":true},"button_padding":{"unit":"px","top":"10","right":"10","bottom":"10","left":"10","isLinked":true},"lightbox_animation":"fade","columns_tablet":"2"},"elements":[],"isInner":false,"widgetType":"bdt-advanced-image-gallery","elType":"widget"}],"isInner":true,"elType":"column"}],"isInner":true,"elType":"section"}],"isInner":false,"elType":"column"}],"isInner":false,"elType":"section"}]}